pylambdalabs/__init__.py
pylambdalabs/cli.py
pylambdalabs-0.1.0.dist-info/LICENSE
pylambdalabs-0.1.0.dist-info/METADATA
pylambdalabs-0.1.0.dist-info/WHEEL
pylambdalabs-0.1.0.dist-info/entry_points.txt
pylambdalabs-0.1.0.dist-info/top_level.txt
pylambdalabs-0.1.0.dist-info/RECORD
